setup.py
enfugue/__init__.py
enfugue/__main__.py
enfugue/enfugue.py
enfugue/server.py
enfugue/version.txt
enfugue.egg-info/PKG-INFO
enfugue.egg-info/SOURCES.txt
enfugue.egg-info/dependency_links.txt
enfugue.egg-info/entry_points.txt
enfugue.egg-info/requires.txt
enfugue.egg-info/top_level.txt
enfugue/api/__init__.py
enfugue/api/config.py
enfugue/api/downloads.py
enfugue/api/manager.py
enfugue/api/server.py
enfugue/api/controller/__init__.py
enfugue/api/controller/base.py
enfugue/api/controller/downloads.py
enfugue/api/controller/invocation.py
enfugue/api/controller/models.py
enfugue/api/controller/system.py
enfugue/api/invocations/__init__.py
enfugue/api/invocations/base.py
enfugue/api/invocations/diffusion.py
enfugue/api/invocations/language.py
enfugue/client/__init__.py
enfugue/client/client.py
enfugue/client/invocation.py
enfugue/config/cms-context.yml
enfugue/config/database.yml
enfugue/config/enfugue.yml
enfugue/config/logging.yml
enfugue/config/server.yml
enfugue/database/__init__.py
enfugue/database/base.py
enfugue/database/config.py
enfugue/database/invocations.py
enfugue/database/models.py
enfugue/diffusion/__init__.py
enfugue/diffusion/constants.py
enfugue/diffusion/engine.py
enfugue/diffusion/manager.py
enfugue/diffusion/pipeline.py
enfugue/diffusion/process.py
enfugue/diffusion/animate/__init__.py
enfugue/diffusion/animate/pipeline.py
enfugue/diffusion/animate/diff/__init__.py
enfugue/diffusion/animate/diff/attention.py
enfugue/diffusion/animate/diff/motion_module.py
enfugue/diffusion/animate/diff/resnet.py
enfugue/diffusion/animate/diff/sparse_controlnet.py
enfugue/diffusion/animate/diff/unet.py
enfugue/diffusion/animate/diff/unet_blocks.py
enfugue/diffusion/animate/diffxl/__init__.py
enfugue/diffusion/animate/diffxl/convert_lora_safetensors_to_diffusers.py
enfugue/diffusion/animate/diffxl/motion_module.py
enfugue/diffusion/animate/diffxl/unet.py
enfugue/diffusion/animate/diffxl/unet_blocks.py
enfugue/diffusion/animate/diffxl/util.py
enfugue/diffusion/animate/diffxl/xl_lora_util.py
enfugue/diffusion/animate/dragnuwa/__init__.py
enfugue/diffusion/animate/dragnuwa/lora.py
enfugue/diffusion/animate/dragnuwa/net.py
