Metadata-Version: 2.1
Name: enfugue
Version: 0.3.3.post3
Author: Benjamin Paine
Author-email: painebenjamin@gmail.com
License: agpl-3.0
Requires-Dist: brotli>=1.0.9
Requires-Dist: cheroot>=9.0.0
Requires-Dist: nvidia-pyindex>=1.0.9
Requires-Dist: pibble[cherrypy]>=0.7.2
Requires-Dist: torch>=1.13.1
Requires-Dist: torchvision>=0.14.1
Requires-Dist: numpy>=1.24.3
Requires-Dist: colored<1.5,>=1.4
Requires-Dist: diffusers>=0.18
Requires-Dist: albumentations<0.5,>=0.4.3
Requires-Dist: pudb==2019.2
Requires-Dist: invisible-watermark<0.3,>=0.2
Requires-Dist: imageio<3.0,>=2.31.1
Requires-Dist: imageio-ffmpeg<0.5,>=0.4.8
Requires-Dist: pytorch-lightning<2.1,>=2.0.5
Requires-Dist: omegaconf<2.2,>=2.1.1
Requires-Dist: test-tube<0.8,>=0.7.5
Requires-Dist: streamlit<0.74,>=0.73
Requires-Dist: einops<0.7,>=0.6.1
Requires-Dist: torch-fidelity<0.4,>=0.3
Requires-Dist: transformers<5.0,>=4.30
Requires-Dist: torchmetrics<1.2,>=1.1
Requires-Dist: kornia<0.7,>=0.6.10
Requires-Dist: accelerate<0.22,>=0.21
Requires-Dist: tqdm>=4.27
Requires-Dist: safetensors<0.4,>=0.3
Requires-Dist: realesrgan<0.4,>=0.3
Requires-Dist: gfpgan<1.4,>=1.3.8
Requires-Dist: beautifulsoup4<5,>=4.12
Requires-Dist: pystray<0.24,>=0.19
Requires-Dist: pydantic==1.10.10
Requires-Dist: pyarrow<13.0,>=12.0.1
Requires-Dist: html2text==2020.1.16
Requires-Dist: torchsde<0.3,>=0.2.5
Requires-Dist: timm<1.0,>=0.9.2
Requires-Dist: opensimplex<0.5,>=0.4.5
Requires-Dist: sentencepiece>=0.1
Requires-Dist: compel>=2.0
Requires-Dist: open-clip-torch>=2.20
Provides-Extra: directml
Requires-Dist: torch-directml==0.1.13.1.dev230413; extra == "directml"
Provides-Extra: xformers
Requires-Dist: xformers>=0.0.20; extra == "xformers"
Provides-Extra: tensorrt
Requires-Dist: polygraphy<0.48,>=0.47; extra == "tensorrt"
Requires-Dist: onnx==1.12; extra == "tensorrt"
Requires-Dist: onnxruntime-gpu==1.12.1; extra == "tensorrt"
Requires-Dist: onnx-graphsurgeon==0.3.26; extra == "tensorrt"
Requires-Dist: tensorrt<8.7,>=8.6.0; extra == "tensorrt"
Provides-Extra: source
Requires-Dist: taming-transformers; extra == "source"
Requires-Dist: clip; extra == "source"
Requires-Dist: latent-diffusion; extra == "source"
Provides-Extra: build
Requires-Dist: mypy==1.2.0; extra == "build"
Requires-Dist: mypy-extensions==1.0.0; extra == "build"
Requires-Dist: types-protobuf<5.0,>=4.23.0.1; extra == "build"
Requires-Dist: types-requests<3.0,>=2.30; extra == "build"
Requires-Dist: types-setuptools<68.0,>=67.7; extra == "build"
Requires-Dist: types-urllib3<2.0,>=1.26.25; extra == "build"
Requires-Dist: types-tabulate<0.10,>=0.9; extra == "build"
Requires-Dist: types-pyyaml<7.0,>=6.0; extra == "build"
Requires-Dist: importchecker<3.0,>=2.0; extra == "build"
Requires-Dist: pyinstaller>=5.13.0; extra == "build"
